Flask_Webpack_Fork-0.1.1.dist-info/DESCRIPTION.rst
Flask_Webpack_Fork-0.1.1.dist-info/METADATA
Flask_Webpack_Fork-0.1.1.dist-info/RECORD
Flask_Webpack_Fork-0.1.1.dist-info/WHEEL
Flask_Webpack_Fork-0.1.1.dist-info/metadata.json
Flask_Webpack_Fork-0.1.1.dist-info/top_level.txt
flask_webpack/__init__.py
