Metadata-Version: 2.0
Name: Flask-Webpack-Fork
Version: 0.1.1
Summary: Flask extension for managing assets with Webpack.
Home-page: https://github.com/5kyc0d3r/flask-webpack
Author: Nick Janetakis, 5kyc0d3r
Author-email: nick.janetakis@gmail.com
License: GPLv3
Platform: UNKNOWN
Requires-Dist: Flask
Requires-Dist: setuptools
